helloworld.py
sub.py
subuxapp-0.0.2.dist-info/LICENSE.txt
subuxapp-0.0.2.dist-info/METADATA
subuxapp-0.0.2.dist-info/WHEEL
subuxapp-0.0.2.dist-info/top_level.txt
subuxapp-0.0.2.dist-info/RECORD
