Metadata-Version: 2.1
Name: subuxapp
Version: 0.0.2
Summary: SubUx module for python
Home-page: https://github.com/python019/sub-module-pypi
Author: Jumayev Ubaydullo
Author-email: tommyjumayev@gmail.com
Classifier: Programming Language :: Python :: 3
Classifier: Programming Language :: Python :: 3.6
Classifier: Programming Language :: Python :: 3.10
License-File: LICENSE.txt
Requires-Dist: blessings (~=1.7)
Provides-Extra: dev
Requires-Dist: pytest (>=3.10) ; extra == 'dev'
